neurolite/__init__.py
neurolite/_version.py
neurolite/api.py
neurolite/cli/__init__.py
neurolite/cli/main.py
neurolite/core/__init__.py
neurolite/core/benchmarks.py
neurolite/core/config.py
neurolite/core/exceptions.py
neurolite/core/logger.py
neurolite/core/performance.py
neurolite/core/plugin_integration.py
neurolite/core/plugin_templates.py
neurolite/core/plugins.py
neurolite/core/utils.py
neurolite/data/__init__.py
neurolite/data/augmentation.py
neurolite/data/cleaner.py
neurolite/data/detector.py
neurolite/data/loader.py
neurolite/data/preprocessor.py
neurolite/data/splitter.py
neurolite/data/validator.py
neurolite/deployment/__init__.py
neurolite/deployment/exporter.py
neurolite/deployment/optimizer.py
neurolite/deployment/server.py
neurolite/deployment/validator.py
neurolite/deployment/formats/__init__.py
neurolite/deployment/formats/base.py
neurolite/deployment/formats/onnx.py
neurolite/deployment/formats/pytorch.py
neurolite/deployment/formats/tflite.py
neurolite/evaluation/__init__.py
neurolite/evaluation/evaluator.py
neurolite/evaluation/metrics.py
neurolite/evaluation/validator.py
neurolite/evaluation/visualizer.py
neurolite/models/__init__.py
neurolite/models/base.py
neurolite/models/factory.py
neurolite/models/registry.py
neurolite/models/dl/__init__.py
neurolite/models/dl/nlp.py
neurolite/models/dl/vision.py
neurolite/models/ml/__init__.py
neurolite/models/ml/ensemble_models.py
neurolite/models/ml/sklearn_models.py
neurolite/models/ml/xgboost_models.py
neurolite/training/__init__.py
neurolite/training/callbacks.py
neurolite/training/config.py
neurolite/training/optimizer.py
neurolite/training/trainer.py
neurolite/visualization/__init__.py
neurolite/visualization/dashboard.py
neurolite/visualization/exporters.py
neurolite/visualization/plots.py
neurolite/visualization/reports.py
neurolite/workflows/__init__.py
neurolite/workflows/base.py
neurolite/workflows/factory.py
neurolite/workflows/nlp.py
neurolite/workflows/tabular.py
neurolite-0.2.0.dist-info/licenses/LICENSE
neurolite-0.2.0.dist-info/METADATA
neurolite-0.2.0.dist-info/WHEEL
neurolite-0.2.0.dist-info/entry_points.txt
neurolite-0.2.0.dist-info/top_level.txt
neurolite-0.2.0.dist-info/RECORD
