Metadata-Version: 2.4
Name: neurolite
Version: 0.2.0
Summary: AI/ML/DL/NLP productivity library for minimal-code machine learning workflows
Home-page: https://github.com/dot-css/neurolite
Author: NeuroLite Team
Author-email: NeuroLite Team <team@neurolite.ai>
License-Expression: MIT
Project-URL: Homepage, https://github.com/dot-css/neurolite
Project-URL: Documentation, https://neurolite.readthedocs.io
Project-URL: Repository, https://github.com/dot-css/neurolite
Project-URL: Bug Tracker, https://github.com/dot-css/neurolite/issues
Keywords: machine learning,deep learning,nlp,computer vision,automation
Classifier: Development Status :: 3 - Alpha
Classifier: Intended Audience :: Developers
Classifier: Intended Audience :: Science/Research
Classifier: Operating System :: OS Independent
Classifier: Programming Language :: Python :: 3
Classifier: Programming Language :: Python :: 3.8
Classifier: Programming Language :: Python :: 3.9
Classifier: Programming Language :: Python :: 3.10
Classifier: Programming Language :: Python :: 3.11
Classifier: Programming Language :: Python :: 3.12
Classifier: Topic :: Scientific/Engineering :: Artificial Intelligence
Classifier: Topic :: Software Development :: Libraries :: Python Modules
Requires-Python: >=3.8
License-File: LICENSE
Requires-Dist: numpy>=1.24.0
Requires-Dist: pandas>=2.0.0
Requires-Dist: scikit-learn>=1.3.0
Requires-Dist: torch>=2.0.0
Requires-Dist: torchvision>=0.15.0
Requires-Dist: transformers>=4.30.0
Requires-Dist: optuna>=3.3.0
Requires-Dist: matplotlib>=3.7.0
Requires-Dist: seaborn>=0.12.0
Requires-Dist: plotly>=5.15.0
Requires-Dist: flask>=2.3.0
Requires-Dist: fastapi>=0.100.0
Requires-Dist: uvicorn>=0.23.0
Requires-Dist: pydantic>=2.0.0
Requires-Dist: click>=8.1.0
Requires-Dist: tqdm>=4.65.0
Requires-Dist: pillow>=10.0.0
Requires-Dist: opencv-python>=4.8.0
Requires-Dist: librosa>=0.10.0
Requires-Dist: onnx>=1.14.0
Requires-Dist: onnxruntime>=1.15.0
Provides-Extra: dev
Requires-Dist: pytest>=7.4.0; extra == "dev"
Requires-Dist: pytest-cov>=4.1.0; extra == "dev"
Requires-Dist: pytest-xdist>=3.3.0; extra == "dev"
Requires-Dist: black>=23.7.0; extra == "dev"
Requires-Dist: flake8>=6.0.0; extra == "dev"
Requires-Dist: mypy>=1.5.0; extra == "dev"
Requires-Dist: pre-commit>=3.3.0; extra == "dev"
Requires-Dist: build>=0.10.0; extra == "dev"
Requires-Dist: twine>=4.0.2; extra == "dev"
Requires-Dist: ruff>=0.0.280; extra == "dev"
Provides-Extra: tensorflow
Requires-Dist: tensorflow>=2.13.0; extra == "tensorflow"
Provides-Extra: xgboost
Requires-Dist: xgboost>=1.7.0; extra == "xgboost"
Provides-Extra: docs
Requires-Dist: sphinx>=7.0.0; extra == "docs"
Requires-Dist: sphinx-rtd-theme>=1.3.0; extra == "docs"
Requires-Dist: myst-parser>=2.0.0; extra == "docs"
Provides-Extra: all
Requires-Dist: neurolite[docs,tensorflow,xgboost]; extra == "all"
Dynamic: author
Dynamic: home-page
Dynamic: license-file
Dynamic: requires-python
